remlalib/__init__.py
remlalib/_version.py
remlalib/preprocess.py
remlalib/version_util.py
remlalib-1.1.8.dist-info/LICENSE.txt
remlalib-1.1.8.dist-info/METADATA
remlalib-1.1.8.dist-info/WHEEL
remlalib-1.1.8.dist-info/top_level.txt
remlalib-1.1.8.dist-info/RECORD
